MANIFEST.in
setup.py
version.txt
doc/README
doc/description.txt
fsc.locker.egg-info/PKG-INFO
fsc.locker.egg-info/SOURCES.txt
fsc.locker.egg-info/dependency_links.txt
fsc.locker.egg-info/requires.txt
fsc.locker.egg-info/top_level.txt
fsc/locker/__init__.py
fsc/locker/_locker.py
fsc/locker/_version.py
fsc/locker/version.txt