Metadata-Version: 1.1
Name: fsc.locker
Version: 1.0.1
Summary: Locker metaclasses to limit attribute changes for Python classes.
